{
  "_comment": "Feed EN VIVO del Mundial 2026. Generado por update_feed.py con API-Football.",
  "updatedAt": "2026-06-15T00:35:36.066964Z",
  "rankings": {
    "ARG": 1,
    "ESP": 2,
    "FRA": 3,
    "ENG": 4,
    "POR": 5,
    "BRA": 6,
    "MAR": 7,
    "NED": 8,
    "BEL": 9,
    "GER": 10,
    "CRO": 11,
    "COL": 13,
    "MEX": 14,
    "SEN": 15,
    "URU": 16,
    "USA": 17,
    "JPN": 18,
    "SUI": 19,
    "IRN": 20,
    "TUR": 22,
    "ECU": 23,
    "AUT": 24,
    "KOR": 25,
    "AUS": 27,
    "ALG": 28,
    "EGY": 29,
    "CAN": 30,
    "NOR": 31,
    "CIV": 33,
    "PAN": 34,
    "SWE": 38,
    "CZE": 40,
    "PAR": 41,
    "SCO": 42,
    "TUN": 45,
    "COD": 46,
    "UZB": 50,
    "QAT": 56,
    "IRQ": 58,
    "RSA": 60,
    "KSA": 61,
    "JOR": 64,
    "CPV": 70,
    "GHA": 73,
    "BIH": 74,
    "HAI": 84,
    "CUR": 85,
    "NZL": 86
  },
  "results": {
    "M001": {
      "homeGoals": 2,
      "awayGoals": 0,
      "finished": true
    },
    "M002": {
      "homeGoals": 2,
      "awayGoals": 1,
      "finished": true
    },
    "M003": {
      "homeGoals": 1,
      "awayGoals": 1,
      "finished": true
    },
    "M004": {
      "homeGoals": 4,
      "awayGoals": 1,
      "finished": true
    },
    "M005": {
      "homeGoals": 1,
      "awayGoals": 1,
      "finished": true
    },
    "M006": {
      "homeGoals": 1,
      "awayGoals": 1,
      "finished": true
    },
    "M007": {
      "homeGoals": 0,
      "awayGoals": 1,
      "finished": true
    },
    "M008": {
      "homeGoals": 2,
      "awayGoals": 0,
      "finished": true
    },
    "M009": {
      "homeGoals": 7,
      "awayGoals": 1,
      "finished": true
    },
    "M010": {
      "homeGoals": 2,
      "awayGoals": 2,
      "finished": true
    },
    "M011": {
      "homeGoals": 0,
      "awayGoals": 0,
      "finished": false,
      "live": true,
      "statusShort": "2H",
      "minute": 70,
      "homeYellow": 3,
      "homeRed": 0,
      "awayYellow": 0,
      "awayRed": 0
    }
  },
  "topScorers": [
    {
      "rank": 1,
      "name": "F. Balogun",
      "teamCode": "USA",
      "club": "",
      "league": "",
      "position": "Delantero",
      "goals": 2,
      "assists": 0,
      "matches": 1
    },
    {
      "rank": 2,
      "name": "Hwang In-Beom",
      "teamCode": "KOR",
      "club": "",
      "league": "",
      "position": "Mediocampista",
      "goals": 1,
      "assists": 1,
      "matches": 1
    },
    {
      "rank": 3,
      "name": "C. Larin",
      "teamCode": "CAN",
      "club": "",
      "league": "",
      "position": "Delantero",
      "goals": 1,
      "assists": 0,
      "matches": 1
    },
    {
      "rank": 4,
      "name": "G. Reyna",
      "teamCode": "USA",
      "club": "",
      "league": "",
      "position": "Mediocampista",
      "goals": 1,
      "assists": 0,
      "matches": 1
    },
    {
      "rank": 5,
      "name": "Oh Hyeon-Gyu",
      "teamCode": "KOR",
      "club": "",
      "league": "",
      "position": "Delantero",
      "goals": 1,
      "assists": 0,
      "matches": 1
    },
    {
      "rank": 6,
      "name": "Maurício",
      "teamCode": "PAR",
      "club": "",
      "league": "",
      "position": "Mediocampista",
      "goals": 1,
      "assists": 0,
      "matches": 1
    },
    {
      "rank": 7,
      "name": "N. Irankunda",
      "teamCode": "AUS",
      "club": "",
      "league": "",
      "position": "Mediocampista",
      "goals": 1,
      "assists": 0,
      "matches": 1
    },
    {
      "rank": 8,
      "name": "J. Lukić",
      "teamCode": "BIH",
      "club": "",
      "league": "",
      "position": "Delantero",
      "goals": 1,
      "assists": 0,
      "matches": 1
    },
    {
      "rank": 9,
      "name": "R. Jiménez",
      "teamCode": "MEX",
      "club": "",
      "league": "",
      "position": "Delantero",
      "goals": 1,
      "assists": 0,
      "matches": 1
    },
    {
      "rank": 10,
      "name": "J. Quiñones",
      "teamCode": "MEX",
      "club": "",
      "league": "",
      "position": "Mediocampista",
      "goals": 1,
      "assists": 0,
      "matches": 1
    },
    {
      "rank": 11,
      "name": "J.  McGinn",
      "teamCode": "SCO",
      "club": "",
      "league": "",
      "position": "Mediocampista",
      "goals": 1,
      "assists": 0,
      "matches": 1
    },
    {
      "rank": 12,
      "name": "I. Saibari",
      "teamCode": "MAR",
      "club": "",
      "league": "",
      "position": "Delantero",
      "goals": 1,
      "assists": 0,
      "matches": 1
    },
    {
      "rank": 13,
      "name": "Boualem Khoukhi",
      "teamCode": "QAT",
      "club": "",
      "league": "",
      "position": "Defensa",
      "goals": 1,
      "assists": 0,
      "matches": 1
    },
    {
      "rank": 14,
      "name": "L. Krejčí",
      "teamCode": "CZE",
      "club": "",
      "league": "",
      "position": "Defensa",
      "goals": 1,
      "assists": 0,
      "matches": 1
    },
    {
      "rank": 15,
      "name": "Vinícius Júnior",
      "teamCode": "BRA",
      "club": "",
      "league": "",
      "position": "Mediocampista",
      "goals": 1,
      "assists": 0,
      "matches": 1
    },
    {
      "rank": 16,
      "name": "C. Metcalfe",
      "teamCode": "AUS",
      "club": "",
      "league": "",
      "position": "Mediocampista",
      "goals": 1,
      "assists": 0,
      "matches": 1
    },
    {
      "rank": 17,
      "name": "B. Embolo",
      "teamCode": "SUI",
      "club": "",
      "league": "",
      "position": "Delantero",
      "goals": 1,
      "assists": 0,
      "matches": 1
    }
  ],
  "bookings": [
    {
      "name": "T. Zwane",
      "teamCode": "RSA",
      "yellow": 0,
      "red": 1,
      "rank": 1
    },
    {
      "name": "S. Sithole",
      "teamCode": "RSA",
      "yellow": 0,
      "red": 1,
      "rank": 2
    },
    {
      "name": "C. Montes",
      "teamCode": "MEX",
      "yellow": 0,
      "red": 1,
      "rank": 3
    },
    {
      "name": "K. McLean",
      "teamCode": "SCO",
      "yellow": 1,
      "red": 0,
      "rank": 4
    },
    {
      "name": "Findlay Curtis",
      "teamCode": "SCO",
      "yellow": 1,
      "red": 0,
      "rank": 5
    },
    {
      "name": "Y. Akgün",
      "teamCode": "TUR",
      "yellow": 1,
      "red": 0,
      "rank": 6
    },
    {
      "name": "A. Arce",
      "teamCode": "PAR",
      "yellow": 1,
      "red": 0,
      "rank": 7
    },
    {
      "name": "Ibañez",
      "teamCode": "BRA",
      "yellow": 1,
      "red": 0,
      "rank": 8
    },
    {
      "name": "Casemiro",
      "teamCode": "BRA",
      "yellow": 1,
      "red": 0,
      "rank": 9
    },
    {
      "name": "Jassem Gaber",
      "teamCode": "QAT",
      "yellow": 1,
      "red": 0,
      "rank": 10
    },
    {
      "name": "J. Lukić",
      "teamCode": "BIH",
      "yellow": 1,
      "red": 0,
      "rank": 11
    },
    {
      "name": "B. Gutiérrez",
      "teamCode": "MEX",
      "yellow": 1,
      "red": 0,
      "rank": 12
    },
    {
      "name": "A. Hickey",
      "teamCode": "SCO",
      "yellow": 1,
      "red": 0,
      "rank": 13
    },
    {
      "name": "J. Cáceres",
      "teamCode": "PAR",
      "yellow": 1,
      "red": 0,
      "rank": 14
    },
    {
      "name": "M. Almirón",
      "teamCode": "PAR",
      "yellow": 1,
      "red": 0,
      "rank": 15
    },
    {
      "name": "Mahmud Abunada",
      "teamCode": "QAT",
      "yellow": 1,
      "red": 0,
      "rank": 16
    },
    {
      "name": "Lee Gi-Hyuk",
      "teamCode": "KOR",
      "yellow": 1,
      "red": 0,
      "rank": 17
    },
    {
      "name": "D. Zakaria",
      "teamCode": "SUI",
      "yellow": 1,
      "red": 0,
      "rank": 18
    },
    {
      "name": "A. Johnston",
      "teamCode": "CAN",
      "yellow": 1,
      "red": 0,
      "rank": 19
    },
    {
      "name": "L. De Fougerolles",
      "teamCode": "CAN",
      "yellow": 1,
      "red": 0,
      "rank": 20
    },
    {
      "name": "N. Katić",
      "teamCode": "BIH",
      "yellow": 1,
      "red": 0,
      "rank": 21
    },
    {
      "name": "E. Demirović",
      "teamCode": "BIH",
      "yellow": 1,
      "red": 0,
      "rank": 22
    },
    {
      "name": "J. Bellegarde",
      "teamCode": "HAI",
      "yellow": 1,
      "red": 0,
      "rank": 23
    }
  ]
}
